{
  "name": "Charlotte Cox",
  "age": 24,
  "address": {
    "street": "Davni Street",
    "city": "Nebejla",
    "state": "TX",
    "zip": "35944"
  },
  "contact": {
    "phone": "(238) 612-6011",
    "servicePhone": "800856146"
  },
  "birthday": "1983-05-31T20:56:50.696Z",
  "ip": "52.183.43.28",
  "foo": "bar",
  "profile": {
    "about": "Dikor gu ti lilrucuh je fouwti efodo dol asehu mu mev hoejha tocir kezlozzuk ho. Ikgivwi je kegi tusonila ahoamo gebaam uga uwe ta sifcu gec bippog penitiz cu. Nozokit azih uc fojeceopa niugaahu zopinaref fum vovav uluka wojzoj dahoknu nigep fi eztute. Agesco kepfi gadisob piwjunu ran ceed ihoepoev fiw uve ek hebit seggocig buolu davo bok.",
    "bio": "Debofu fa zet jak def lef zo asewav kupjaj hihiw pebekuc jok oge zetmoek tugetse cev ejipenso. Keb konissa kizevadu gugo vodvok nu veklebce nitavfaz tu vuke vaawo deor gi up fefkoer ed nadhim. Keflozmap zofjaipi si tunezgu maceah latotuh ta kubbaslo ca er vuduoh usari we re. Nihe ho banab burma zivhoca rij lok gi hefkij joritmo fo sij vim gadifvu fag siravhi nufkovuli gadon. Bajo kes vi gunvuhol mum gu koop op tutofda une pihaj wujuliko."
  },
  "apiKey": "c48b3c9b76adea4c970717d2db851503440d0416fe2cdb1d475eaec39c08f7a4",
  "currency": {
    "code": "AOA",
    "name": "Angola Kwanza"
  }
}