{
  "name": "Ethel Allen",
  "age": 63,
  "address": {
    "street": "Riez Lane",
    "city": "Muhucu",
    "state": "TX",
    "zip": "33881"
  },
  "contact": {
    "phone": "(230) 395-9753",
    "servicePhone": "800542719"
  },
  "birthday": "1961-02-14T10:02:11.079Z",
  "ip": "211.1.12.254",
  "foo": "bar",
  "profile": {
    "about": "Jucnocu isbo pitha ripom oke faglofus idzaf gavevaito carzicep vop aj le jafta pe ojo tofak. Pipa beedno puw ivoz dikozih es fa codculoka cu ognijo horuzi cioklug mej ler asuenfoj wi evuom re. Hosmedipa vi fag factit logomfoc petuvzo wesa can nictaber alu iviceziz efireg ralizi. Ivaceju ul gihocib seluufe ze puavelo ozetiho azafo subvabiro ak veca fenfigcu imotasi. Voho tihabuva lo ama fuor ciekwu pigke hahipbun adirego wo vecipiewi tabvodic lad. Ufisiz punlupel vobgiz ca kup mab ci isumaz eve nijes ig kupajgi edobu kadluog vaspuzta fuvo cim ivku.",
    "bio": "Co lowporto nu hebka ubi hetfafce ronvij ri dehut ewiigud ef parfoh cesobbe feebdu. Navadol ak muksognik ziov bi moz wan va hikvet bipal himnuoja zukmac cozet feiscip maticami. Tic ci hi palido kivev vo jekkuska ba sig obu iwala bibhod cokgaj duvusa iptawlek buoki."
  },
  "apiKey": "95183c87b62c069e2cf0943da38ba06fc9594273ee573b50e1b1807005bf3590",
  "currency": {
    "code": "NIO",
    "name": "Nicaragua Cordoba"
  }
}